erdc_quest-3.0.1.dist-info/DESCRIPTION.rst
erdc_quest-3.0.1.dist-info/METADATA
erdc_quest-3.0.1.dist-info/RECORD
erdc_quest-3.0.1.dist-info/WHEEL
erdc_quest-3.0.1.dist-info/metadata.json
erdc_quest-3.0.1.dist-info/pbr.json
erdc_quest-3.0.1.dist-info/top_level.txt
quest/__init__.py
quest/api/__init__.py
quest/api/catalog.py
quest/api/collections.py
quest/api/datasets.py
quest/api/manage.py
quest/api/metadata.py
quest/api/parameters.py
quest/api/projects.py
quest/api/providers.py
quest/api/tasks.py
quest/api/tools.py
quest/api/version.py
quest/api/workflows.py
quest/database/__init__.py
quest/database/database.py
quest/plugins/__init__.py
quest/plugins/plugins.py
quest/plugins/user_provider.py
quest/plugins/base/__init__.py
quest/plugins/base/io_base.py
quest/plugins/base/provider_base.py
quest/plugins/base/publish_base.py
quest/plugins/base/service_base.py
quest/plugins/base/tool_base.py
quest/static/__init__.py
quest/tools/__init__.py
quest/util/__init__.py
quest/util/config.py
quest/util/io.py
quest/util/log.py
quest/util/misc.py
quest/util/param_util.py
quest/util/units/__init__.py
quest/util/units/constants_en.txt
quest/util/units/default_units.txt
quest_io_plugins/__init__.py
quest_io_plugins/raster_gdal.py
quest_io_plugins/timeseries_hdf5.py
quest_io_plugins/xyHdf5.py
quest_provider_plugins/__init__.py
quest_provider_plugins/cuahsi_hs.py
quest_provider_plugins/kitware_girder.py
quest_provider_plugins/nasa.py
quest_provider_plugins/noaa_coastwatch.py
quest_provider_plugins/noaa_ncdc.py
quest_provider_plugins/quest_catalog.py
quest_provider_plugins/usgs_ned.py
quest_provider_plugins/usgs_nlcd.py
quest_provider_plugins/usgs_nwis.py
quest_provider_plugins/wmts_imagery.py
quest_tool_plugins/__init__.py
quest_tool_plugins/raster/__init__.py
quest_tool_plugins/raster/raster.py
quest_tool_plugins/raster/rst_base.py
quest_tool_plugins/raster/rst_merge.py
quest_tool_plugins/raster/rst_reprojection.py
quest_tool_plugins/timeseries/__init__.py
quest_tool_plugins/timeseries/timeseries.py
quest_tool_plugins/timeseries/ts_base.py
quest_tool_plugins/timeseries/ts_flow_duration.py
quest_tool_plugins/whitebox/__init__.py
quest_tool_plugins/whitebox/whitebox_utils.py
