Metadata-Version: 2.0
Name: erdc-quest
Version: 3.0.1
Summary: Extensible API for downloading and managing data
Home-page: https://github.com/erdc/quest
Author: Aaron Valoroso
Author-email: aaron.a.valoroso@usace.army.mil
License: UNKNOWN
Platform: UNKNOWN
Classifier: Development Status :: 3 - Alpha
Classifier: Intended Audience :: Science/Research
Classifier: Operating System :: OS Independent
Classifier: Programming Language :: Python
Classifier: Topic :: Software Development :: Libraries :: Python Modules
Provides-Extra: docs
Requires-Dist: sphinx; extra == 'docs'
Requires-Dist: sphinx-rtd-theme; extra == 'docs'
Requires-Dist: pbr; extra == 'docs'
Requires-Dist: appdirs; extra == 'docs'
Provides-Extra: tests
Requires-Dist: pytest; extra == 'tests'
